korsair-api/__init__.py
korsair-api/korsair.py
korsair_api/__init__.py
korsair_api/korsair.py
korsair_api-1.1.5.dist-info/LICENSE
korsair_api-1.1.5.dist-info/METADATA
korsair_api-1.1.5.dist-info/WHEEL
korsair_api-1.1.5.dist-info/top_level.txt
korsair_api-1.1.5.dist-info/RECORD
